{
    "boxShadow": "{{appsmith.theme.boxShadow.appBoxShadow}}",
    "widgetName": "Tabs1",
    "isCanvas": true,
    "displayName": "Tabs",
    "iconSVG": "/static/media/icon.74a6d653.svg",
    "topRow": 20,
    "bottomRow": 65,
    "parentRowSpace": 10,
    "type": "TABS_WIDGET",
    "hideCard": false,
    "shouldScrollContents": false,
    "animateLoading": true,
    "parentColumnSpace": 28.921875,
    "dynamicTriggerPathList": [],
    "leftColumn": 34,
    "dynamicBindingPathList": [
        {"key": "defaultTab"},
        {"key": "borderRadius"},
        {"key": "boxShadow"}
    ],
    "children": [
        {
            "tabId": "tab1",
            "boxShadow": "none",
            "widgetName": "Canvas3",
            "displayName": "Canvas",
            "topRow": 0,
            "bottomRow": 450,
            "parentRowSpace": 1,
            "type": "CANVAS_WIDGET",
            "canExtend": true,
            "hideCard": true,
            "shouldScrollContents": false,
            "minHeight": 400,
            "parentColumnSpace": 1,
            "leftColumn": 0,
            "dynamicBindingPathList": [],
            "isDisabled": false,
            "key": "atuqtbl6c4",
            "labelTextSize": "0.875rem",
            "tabName": "Tab 1",
            "rightColumn": 694.125,
            "detachFromLayout": true,
            "widgetId": "2dnjzb938w",
            "isVisible": true,
            "version": 1,
            "parentId": "aosj4kggzl",
            "renderMode": "CANVAS",
            "isLoading": false,
            "borderRadius": "0px"
        },
        {
            "tabId": "tab2",
            "boxShadow": "none",
            "widgetName": "Canvas4",
            "displayName": "Canvas",
            "topRow": 0,
            "bottomRow": 450,
            "parentRowSpace": 1,
            "type": "CANVAS_WIDGET",
            "canExtend": true,
            "hideCard": true,
            "shouldScrollContents": false,
            "minHeight": 400,
            "parentColumnSpace": 1,
            "leftColumn": 0,
            "dynamicBindingPathList": [],
            "isDisabled": false,
            "key": "atuqtbl6c4",
            "labelTextSize": "0.875rem",
            "tabName": "Tab 2",
            "rightColumn": 694.125,
            "detachFromLayout": true,
            "widgetId": "m87xf4m11k",
            "isVisible": true,
            "version": 1,
            "parentId": "aosj4kggzl",
            "renderMode": "CANVAS",
            "isLoading": false,
            "borderRadius": "0px"
        }
    ],
    "key": "c67dxhi6nm",
    "labelTextSize": "0.875rem",
    "rightColumn": 60,
    "dynamicHeight": "FIXED",
    "widgetId": "aosj4kggzl",
    "accentColor": "{{appsmith.theme.colors.primaryColor}}",
    "defaultTab": "{{Table1.selectedRowIndex == -1 ? \"Tab 1\" : \"Tab 2\"}}",
    "shouldShowTabs": false,
    "tabsObj": {
        "tab1": {
            "widgetId": "2dnjzb938w",
            "index": 0,
            "label": "Tab 1",
            "id": "tab1",
            "isVisible": true
        },
        "tab2": {
            "widgetId": "m87xf4m11k",
            "index": 1,
            "label": "Tab 2",
            "id": "tab2",
            "isVisible": true
        }
    },
    "isVisible": true,
    "version": 3,
    "parentId": "0",
    "renderMode": "CANVAS",
    "isLoading": false,
    "borderRadius": "{{appsmith.theme.borderRadius.appBorderRadius}}",
    "maxDynamicHeight": 9000,
    "minDynamicHeight": 4
}